{
  "slug": "adialante",
  "name": "Adialante",
  "oneLiner": "Cancer screening without barriers",
  "metadata": {
    "website": "http://www.adialante.com",
    "yc_page": "https://www.ycombinator.com/companies/adialante",
    "batch": "Spring 2026 (YC S26/P26)",
    "industry": "Healthcare / Healthcare -> Diagnostics",
    "team_size": "4 (YC listing); company website lists 6 named team members",
    "location": "Redwood City, CA, USA",
    "tags": "Hardware, Medical Devices, Health & Wellness",
    "yc_partner": "Nicolas Dessaigne (YC company page)",
    "emails": "clinics@adialante.com (adialante.com)"
  },
  "tags": [
    "Hardware",
    "Medical Devices",
    "Health & Wellness"
  ],
  "slideImage": null,
  "memoGeneratedAt": "2026-05-28T02:50:44.711Z",
  "evalScores": {
    "cyan-banister": {
      "score": 74,
      "tier": "Invest"
    },
    "elad-gil": {
      "score": 39,
      "tier": "Pass"
    }
  },
  "consolidatedScores": {
    "CB": 74,
    "EG": 39,
    "NR": null,
    "PG": null,
    "PT": null,
    "SL": null,
    "VK": null
  },
  "consolidatedAvg": 56.5,
  "consolidatedRank": 20,
  "paths": {
    "memo": "spring2026/memos/adialante.md",
    "evals": {
      "cyan-banister": "spring2026/evals/cyan-banister/adialante.md",
      "elad-gil": "spring2026/evals/elad-gil/adialante.md"
    }
  }
}