{
  "slug": "clara-2",
  "name": "Clara",
  "oneLiner": "AI primary care doctor",
  "metadata": {
    "website": "http://askclara.com",
    "yc_page": "https://www.ycombinator.com/companies/clara-2",
    "batch": "Spring 2026",
    "industry": "Healthcare / Consumer Health and Wellness",
    "team_size": "9",
    "location": "San Francisco, CA, USA",
    "tags": "Telehealth, Healthcare, Telemedicine, AI",
    "yc_partner": "Garry Tan",
    "emails": "No public data found"
  },
  "tags": [
    "Telehealth",
    "Healthcare",
    "Telemedicine",
    "AI"
  ],
  "slideImage": null,
  "memoGeneratedAt": "2026-03-26T17:06:25.444Z",
  "evalScores": {
    "cyan-banister": {
      "score": 52,
      "tier": "Neutral"
    },
    "elad-gil": {
      "score": 66,
      "tier": "Invest"
    },
    "naval-ravikant": {
      "score": 62,
      "tier": "Neutral"
    },
    "paul-graham": {
      "score": 56,
      "tier": "Neutral"
    },
    "peter-thiel": {
      "score": 38,
      "tier": "Pass"
    },
    "sam-lessin": {
      "score": 37,
      "tier": "Pass"
    },
    "vinod-khosla": {
      "score": 60,
      "tier": "Neutral"
    }
  },
  "consolidatedScores": {
    "CB": 52,
    "EG": 66,
    "NR": 62,
    "PG": 56,
    "PT": 38,
    "SL": 37,
    "VK": 60
  },
  "consolidatedAvg": 53,
  "consolidatedRank": 5,
  "paths": {
    "memo": "spring2026/memos/clara-2.md",
    "evals": {
      "cyan-banister": "spring2026/evals/cyan-banister/clara-2.md",
      "elad-gil": "spring2026/evals/elad-gil/clara-2.md",
      "naval-ravikant": "spring2026/evals/naval-ravikant/clara-2.md",
      "paul-graham": "spring2026/evals/paul-graham/clara-2.md",
      "peter-thiel": "spring2026/evals/peter-thiel/clara-2.md",
      "sam-lessin": "spring2026/evals/sam-lessin/clara-2.md",
      "vinod-khosla": "spring2026/evals/vinod-khosla/clara-2.md"
    }
  }
}