{
  "slug": "strand-ai",
  "name": "Strand AI",
  "oneLiner": "Curated multimodal datasets for biology AI",
  "metadata": {
    "website": "https://strandai.com",
    "yc_page": "https://www.ycombinator.com/companies/strand-ai",
    "batch": "Winter 2026",
    "industry": "Healthcare / Healthcare -> Drug Discovery and Delivery",
    "team_size": "2",
    "location": "San Francisco, CA, USA",
    "tags": "Artificial Intelligence, Generative AI, Biotech",
    "yc_partner": "Jon Xu",
    "emails": "founders@strandai.com"
  },
  "tags": [
    "Artificial Intelligence",
    "Generative AI",
    "Biotech"
  ],
  "slideImage": null,
  "memoGeneratedAt": "2026-03-05T01:11:36.873Z",
  "evalScores": {
    "cyan-banister": {
      "score": 45,
      "tier": "Neutral"
    },
    "elad-gil": {
      "score": 54,
      "tier": "Neutral"
    },
    "naval-ravikant": {
      "score": 67,
      "tier": "Invest"
    },
    "paul-graham": {
      "score": 59,
      "tier": "Neutral"
    },
    "peter-thiel": {
      "score": 42,
      "tier": "Pass"
    },
    "sam-lessin": {
      "score": 37,
      "tier": "Pass"
    },
    "vinod-khosla": {
      "score": 58,
      "tier": "Neutral"
    }
  },
  "consolidatedScores": {
    "CB": 45,
    "EG": 54,
    "NR": 67,
    "PG": 59,
    "PT": 42,
    "SL": 37,
    "VK": 58
  },
  "consolidatedAvg": 51.71,
  "consolidatedRank": 29,
  "paths": {
    "memo": "winter2026/memos/strand-ai.md",
    "evals": {
      "cyan-banister": "winter2026/evals/cyan-banister/strand-ai.md",
      "elad-gil": "winter2026/evals/elad-gil/strand-ai.md",
      "naval-ravikant": "winter2026/evals/naval-ravikant/strand-ai.md",
      "paul-graham": "winter2026/evals/paul-graham/strand-ai.md",
      "peter-thiel": "winter2026/evals/peter-thiel/strand-ai.md",
      "sam-lessin": "winter2026/evals/sam-lessin/strand-ai.md",
      "vinod-khosla": "winter2026/evals/vinod-khosla/strand-ai.md"
    }
  }
}